README.rst
setup.py
os0/__init__.py
os0/__main__.py
os0/os0core.py
os0/setup.py
os0.egg-info/PKG-INFO
os0.egg-info/SOURCES.txt
os0.egg-info/dependency_links.txt
os0.egg-info/not-zip-safe
os0.egg-info/top_level.txt